proliphix/__init__.py
proliphix/proliphix.py
proliphix-0.4.0.dist-info/top_level.txt
proliphix-0.4.0.dist-info/METADATA
proliphix-0.4.0.dist-info/DESCRIPTION.rst
proliphix-0.4.0.dist-info/metadata.json
proliphix-0.4.0.dist-info/WHEEL
proliphix-0.4.0.dist-info/RECORD
