Metadata-Version: 2.0
Name: proliphix
Version: 0.4.0
Summary: API for Proliphix nt10e network thermostat.
Home-page: https://github.com/sdague/proliphix
Author: Sean Dague
Author-email: sean@dague.net
License: Apache v2
Keywords: proliphix
Platform: UNKNOWN
Classifier: Development Status :: 2 - Pre-Alpha
Classifier: Intended Audience :: Developers
Classifier: License :: OSI Approved :: Apache Software License
Classifier: Natural Language :: English
Classifier: Programming Language :: Python :: 3
Classifier: Programming Language :: Python :: 3.3
Classifier: Programming Language :: Python :: 3.4
Classifier: Programming Language :: Python :: 3.5
Requires-Dist: requests
